{"is_source_file": false, "format": "", "description": "", "external_files": [], "external_methods": [], "published": [], "classes": [], "methods": [], "calls": [], "search-terms": [], "state": 2, "file_id": 32, "knowledge_revision": 74, "git_revision": "201675f480c16825d1754744fe85aa75de13d947", "hash": "32b13deb1e8e3a5988dcf4dccb67a3c8", "format-version": 4, "code-base-name": "dsp_frontend", "filename": "dsp_backend/README.md", "revision_history": [{"74": "201675f480c16825d1754744fe85aa75de13d947"}]}